{
  "project_info": {
    "project_number": "186686870547",
    "project_id": "travel-diary-fcf1f",
    "storage_bucket": "travel-diary-fcf1f.appspot.com"
  },
  "client": [
    {
      "client_info": {
        "mobilesdk_app_id": "1:186686870547:android:7ae3393832dc6ec7fc5be6",
        "android_client_info": {
          "package_name": "com.example.traveldiary.android"
        }
      },
      "oauth_client": [],
      "api_key": [
        {
          "current_key": "AIzaSyBZJPHuopeHRIxLx-ephenJQshPH0O5z0o"
        }
      ],
      "services": {
        "appinvite_service": {
          "other_platform_oauth_client": []
        }
      }
    }
  ],
  "configuration_version": "1"
}